kwmatcher-0.1.2.dist-info/METADATA
kwmatcher-0.1.2.dist-info/WHEEL
kwmatcher-0.1.2.dist-info/licenses/LICENSE
kwmatcher.libs/libgcc_s-b5472b99.so.1
kwmatcher/py.typed
kwmatcher/__init__.py
kwmatcher/kwmatcher.pyi
kwmatcher/kwmatcher.pypy311-pp73-x86-linux-gnu.so
kwmatcher-0.1.2.dist-info/RECORD
