Metadata-Version: 2.4
Name: kwmatcher
Version: 0.1.2
Classifier: Programming Language :: Rust
Classifier: Programming Language :: Python :: Implementation :: CPython
Classifier: Programming Language :: Python :: Implementation :: PyPy
License-File: LICENSE
Author: Raven95676
License: MIT
Requires-Python: >=3.8
